README.md
setup.cfg
setup.py
dist123/Binomialdistribution.py
dist123/Gaussiandistribution.py
dist123/Generaldistribution.py
dist123/__init__.py
dist123.egg-info/PKG-INFO
dist123.egg-info/SOURCES.txt
dist123.egg-info/dependency_links.txt
dist123.egg-info/not-zip-safe
dist123.egg-info/top_level.txt