Metadata-Version: 1.0
Name: dist123
Version: 0.1
Summary: Gaussian distributions
Home-page: UNKNOWN
Author: Shyam Khokhariya
Author-email: UNKNOWN
License: UNKNOWN
Platform: UNKNOWN
